wholemail/__init__.py
wholemail/email_code_verifier.py
wholemail/email_sender.py
wholemail/email_template.py
wholemail/email_worker.py
wholemail/exceptions.py
wholemail/pre_set_email_templates.py
wholemail/template_loader.py
wholemail/template_styles.py
wholemail-0.1.8.dist-info/METADATA
wholemail-0.1.8.dist-info/WHEEL
wholemail-0.1.8.dist-info/top_level.txt
wholemail-0.1.8.dist-info/RECORD
