Metadata-Version: 2.4
Name: wholemail
Version: 0.1.8
Summary: A lucid Python package built to facilitate easy sending of emails and other common generic functionality like sending authentication code emails
Home-page: https://github.com/victhepythonista/wholemail
Author: Victor Kipkemboi
Author-email: scriptilapia@gmail.com
Project-URL: Bug Tracker, https://github.com/victhepythonista/wholemail/issues
Classifier: Programming Language :: Python :: 3
Classifier: License :: OSI Approved :: MIT License
Requires-Python: >=3.6
Requires-Dist: Jinja2
Requires-Dist: code_monger
Requires-Dist: bs4
Dynamic: author
Dynamic: author-email
Dynamic: classifier
Dynamic: description
Dynamic: description-content-type
Dynamic: home-page
Dynamic: project-url
Dynamic: requires-dist
Dynamic: requires-python
Dynamic: summary
